CHANGES.txt
LICENSE.txt
MANIFEST.in
setup.cfg
setup.py
chatfirst/__init__.py
chatfirst/auth.py
chatfirst/client.py
chatfirst/models.py
chatfirst/utils.py
chatfirst.egg-info/PKG-INFO
chatfirst.egg-info/SOURCES.txt
chatfirst.egg-info/dependency_links.txt
chatfirst.egg-info/requires.txt
chatfirst.egg-info/top_level.txt