Metadata-Version: 1.0
Name: chatfirst
Version: 0.2
Summary: Chatfirst Python Client
Home-page: https://github.com/chatfirst/chatfirst
Author: Ivan Tertychnyy
Author-email: it@chatfirst.co
License: LICENSE.txt
Platform: UNKNOWN
